<?xml version="1.0" encoding="utf-8" ?>
<dwsync>
<file name="README.md" server="ftp.pmmaterlandia.mg.gov.br" local="131456283882929614" remote="131375258400000000" Dst="1" />
<file name="LICENSE.md" server="ftp.pmmaterlandia.mg.gov.br" local="131456283883320504" remote="131375258400000000" Dst="1" />
<file name="build-config.js" server="ftp.pmmaterlandia.mg.gov.br" local="131456283889385157" remote="131375258400000000" Dst="1" />
<file name="CHANGES.md" server="ftp.pmmaterlandia.mg.gov.br" local="131456283890891698" remote="131375258400000000" Dst="1" />
<file name="config.js" server="ftp.pmmaterlandia.mg.gov.br" local="131456283891315993" remote="131375258400000000" Dst="1" />
<file name="contents.css" server="ftp.pmmaterlandia.mg.gov.br" local="131456283893282732" remote="131375258400000000" Dst="1" />
<file name="ckeditor.js" server="ftp.pmmaterlandia.mg.gov.br" local="131456283909119740" remote="131375258400000000" Dst="1" />
<file name="styles.js" server="ftp.pmmaterlandia.mg.gov.br" local="131456284443386071" remote="131375258400000000" Dst="1" />
</dwsync>